AUTHORS.rst
CHANGES.rst
LICENSE.txt
MANIFEST.in
README.rst
setup.py
django_sorted_m2m.egg-info/PKG-INFO
django_sorted_m2m.egg-info/SOURCES.txt
django_sorted_m2m.egg-info/dependency_links.txt
django_sorted_m2m.egg-info/not-zip-safe
django_sorted_m2m.egg-info/top_level.txt
sortedm2m/__init__.py
sortedm2m/compat.py
sortedm2m/fields.py
sortedm2m/forms.py
sortedm2m/models.py
sortedm2m/operations.py
sortedm2m/locale/cs/LC_MESSAGES/django.mo
sortedm2m/locale/cs/LC_MESSAGES/django.po
sortedm2m/locale/fr/LC_MESSAGES/django.mo
sortedm2m/locale/fr/LC_MESSAGES/django.po
sortedm2m/static/sortedm2m/jquery-ui.js
sortedm2m/static/sortedm2m/selector-search.gif
sortedm2m/static/sortedm2m/widget.css
sortedm2m/static/sortedm2m/widget.js
sortedm2m/templates/sortedm2m/sorted_checkbox_select_multiple_widget.html